<?xml version="1.0" encoding="utf-8" ?><dwsync><file name="account.php" server="Macintosh HD/Applications/MAMP/htdocs/Shubiri/" local="3556256897" remote="3556256897" Dst="-1" /><file name="connessione_sql.php" server="Macintosh HD/Applications/MAMP/htdocs/Shubiri/" local="3556086029" remote="3556086029" Dst="-1" /><file name="crea-pagina.php" server="Macintosh HD/Applications/MAMP/htdocs/Shubiri/" local="3556264627" remote="3556264627" Dst="-1" /><file name="home.php" server="Macintosh HD/Applications/MAMP/htdocs/Shubiri/" local="3556264180" remote="3556264180" Dst="-1" /><file name="login.php" server="Macintosh HD/Applications/MAMP/htdocs/Shubiri/" local="3556257516" remote="3556257516" Dst="-1" /><file name="pagina.php" server="Macintosh HD/Applications/MAMP/htdocs/Shubiri/" local="3556196118" remote="3556196118" Dst="-1" /><file name="dashboard.php" server="Macintosh HD/Applications/MAMP/htdocs/Shubiri/" local="3556196417" remote="3556196417" Dst="-1" /><file name="htaccess.php" server="Macintosh HD/Applications/MAMP/htdocs/Shubiri/" local="3556258624" remote="3556258624" Dst="-1" /></dwsync>