<?xml version="1.0" encoding="utf-8" ?><dwsync><file name="account.php" server="Macintosh HD/Applications/MAMP/htdocs/Shubiri/" local="3556705752" remote="3556705752" Dst="-1" /><file name="connessione_sql.php" server="Macintosh HD/Applications/MAMP/htdocs/Shubiri/" local="3556705752" remote="3556705752" Dst="-1" /><file name="crea-pagina.php" server="Macintosh HD/Applications/MAMP/htdocs/Shubiri/" local="3556705752" remote="3556705752" Dst="-1" /><file name="home.php" server="Macintosh HD/Applications/MAMP/htdocs/Shubiri/" local="3556705752" remote="3556705752" Dst="-1" /><file name="login.php" server="Macintosh HD/Applications/MAMP/htdocs/Shubiri/" local="3556705752" remote="3556705752" Dst="-1" /><file name="pagina.php" server="Macintosh HD/Applications/MAMP/htdocs/Shubiri/" local="3556705752" remote="3556705752" Dst="-1" /><file name="dashboard.php" server="Macintosh HD/Applications/MAMP/htdocs/Shubiri/" local="3556705752" remote="3556705752" Dst="-1" /><file name="htaccess.php" server="Macintosh HD/Applications/MAMP/htdocs/Shubiri/" local="3556705752" remote="3556705752" Dst="-1" /><file name="connessione_sql.php" server="Macintosh HD/Applications/MAMP/htdocs/blancdesir/" local="3556265643" remote="3556265643" Dst="-1" /></dwsync>